taskiq_pipelines/__init__.py
taskiq_pipelines/abc.py
taskiq_pipelines/constants.py
taskiq_pipelines/exceptions.py
taskiq_pipelines/middleware.py
taskiq_pipelines/pipeliner.py
taskiq_pipelines/py.typed
taskiq_pipelines/steps/__init__.py
taskiq_pipelines/steps/filter.py
taskiq_pipelines/steps/mapper.py
taskiq_pipelines/steps/sequential.py
taskiq_pipelines-0.1.4.dist-info/LICENSE
taskiq_pipelines-0.1.4.dist-info/METADATA
taskiq_pipelines-0.1.4.dist-info/WHEEL
taskiq_pipelines-0.1.4.dist-info/RECORD
