Metadata-Version: 2.3
Name: taskiq-pipelines
Version: 0.1.4
Summary: Taskiq pipelines for task chaining.
License: LICENSE
Keywords: taskiq,pipelines,tasks,distributed,async
Author: Pavel Kirilin
Author-email: win10@list.ru
Requires-Python: >=3.9,<4.0
Classifier: Development Status :: 3 - Alpha
Classifier: Intended Audience :: Developers
Classifier: License :: Other/Proprietary License
Classifier: Operating System :: OS Independent
Classifier: Programming Language :: Python
Classifier: Programming Language :: Python :: 3
Classifier: Programming Language :: Python :: 3.9
Classifier: Programming Language :: Python :: 3.10
Classifier: Programming Language :: Python :: 3.11
Classifier: Programming Language :: Python :: 3.12
Classifier: Programming Language :: Python :: 3.13
Classifier: Programming Language :: Python :: 3 :: Only
Classifier: Topic :: System :: Networking
Classifier: Typing :: Typed
Requires-Dist: pydantic (>=2,<3)
Requires-Dist: taskiq (>=0.11.12,<1)
Requires-Dist: typing-extensions (>=4.3.0,<5.0.0)
Project-URL: Homepage, https://github.com/taskiq-python/taskiq-pipelines
Project-URL: Repository, https://github.com/taskiq-python/taskiq-pipelines
